LICENCE.txt
MANIFEST.in
README.rst
setup.py
bazar/__init__.py
bazar/admin.py
bazar/assets.py
bazar/crumbs.py
bazar/markup.py
bazar/models.py
bazar/settings.py
bazar/urls.py
bazar/forms/__init__.py
bazar/forms/crispies.py
bazar/forms/entity.py
bazar/forms/note.py
bazar/locale/es/LC_MESSAGES/django.mo
bazar/locale/es/LC_MESSAGES/django.po
bazar/locale/fr/LC_MESSAGES/django.mo
bazar/locale/fr/LC_MESSAGES/django.po
bazar/migrations/0001_initial.py
bazar/migrations/0002_extend_entity_phone_fields.py
bazar/migrations/__init__.py
bazar/south_migrations/0001_initial.py
bazar/south_migrations/0002_auto__add_field_entity_fax.py
bazar/south_migrations/0003_auto__add_field_note_file.py
bazar/south_migrations/__init__.py
bazar/static/css/bazar_app.css
bazar/static/css/jquery.tagsinput.css
bazar/static/js/jquery/jquery.tagsinput.js
bazar/static/js/jquery/jquery.tagsinput.min.js
bazar/templates/bazar/base.html
bazar/templates/bazar/include_css.html
bazar/templates/bazar/include_js.html
bazar/templates/bazar/index.html
bazar/templates/bazar/pagination.html
bazar/templates/bazar/entity/detail.html
bazar/templates/bazar/entity/form.html
bazar/templates/bazar/entity/index.html
bazar/templates/bazar/markup/_text_field_djangocodemirror_js.html
bazar/templates/bazar/markup/_text_markup_render.html
bazar/templates/bazar/note/_attachment_download.html
bazar/templates/bazar/note/delete_form.html
bazar/templates/bazar/note/detail.html
bazar/templates/bazar/note/form.html
bazar/templates/bazar/note/list.html
bazar/templatetags/__init__.py
bazar/templatetags/bazar_tags.py
bazar/utils/__init__.py
bazar/utils/filefield.py
bazar/utils/imports.py
bazar/utils/mixins.py
bazar/utils/views.py
bazar/views/__init__.py
bazar/views/entity.py
bazar/views/note.py
emencia_django_bazar.egg-info/PKG-INFO
emencia_django_bazar.egg-info/SOURCES.txt
emencia_django_bazar.egg-info/dependency_links.txt
emencia_django_bazar.egg-info/not-zip-safe
emencia_django_bazar.egg-info/requires.txt
emencia_django_bazar.egg-info/top_level.txt